libarx-0.4.1.dist-info/METADATA
libarx-0.4.1.dist-info/WHEEL
libarx-0.4.1.dist-info/licenses/LICENSE-MIT
libarx/__init__.py
libarx/libarx.cpython-310-x86_64-linux-gnu.so
libarx-0.4.1.dist-info/RECORD
