Metadata-Version: 2.4
Name: libarx
Version: 0.4.1
Classifier: License :: OSI Approved :: MIT License
Classifier: Programming Language :: Rust
Classifier: Programming Language :: Python :: Implementation :: CPython
Classifier: Programming Language :: Python :: Implementation :: PyPy
License-File: LICENSE-MIT
Summary: Read and create arx archives.
Home-Page: https://github.com/jubako/arx
Requires-Python: >=3.8
